simqle/__init__.py
simqle/connection_manager.py
simqle/connections.py
simqle/constants.py
simqle/exceptions.py
simqle/functions.py
simqle/internal.py
simqle/sql_tools.py
tests/__init__.py
tests/integration-tests/__init__.py
tests/integration-tests/conftest.py
tests/integration-tests/test_recordset.py
tests/unit-tests/__init__.py
tests/unit-tests/conftest.py
tests/unit-tests/test_connections.py
tests/unit-tests/test_functions.py
tests/unit-tests/test_simqle.py
tests/unit-tests/test_sql_tools.py
simqle-0.3.0.dist-info/LICENSE
simqle-0.3.0.dist-info/METADATA
simqle-0.3.0.dist-info/WHEEL
simqle-0.3.0.dist-info/top_level.txt
simqle-0.3.0.dist-info/RECORD
