Metadata-Version: 2.1
Name: simqle
Version: 0.3.0
Summary: The simple way to SQL
Home-page: https://github.com/Harlekuin/SimQLe
Author: Tom Malkin
Author-email: tommalkin28@gmail.com
Maintainer: Tom Malkin
Maintainer-email: tommalkin28@gmail.com
License: MIT
Keywords: sql
Platform: UNKNOWN
Classifier: Development Status :: 4 - Beta
Classifier: Intended Audience :: Developers
Classifier: License :: OSI Approved :: MIT License
Classifier: Natural Language :: English
Classifier: Operating System :: OS Independent
Classifier: Programming Language :: Python :: 3.5
Classifier: Programming Language :: Python :: 3.6
Requires-Dist: sqlalchemy
Requires-Dist: pyyaml
